[
  {
    "url": "https://www.berlin.de/polizei/service/vermissen-sie-ihr-fahrrad/artikel.758543.php",
    "description": "Bronzefarbener Damenfahrrad-Rahmen mit Reifen",
    "image": "https://www.berlin.de/polizei/service/vermissen-sie-ihr-fahrrad/fahrradteile/",
    "operation_number": "181109-0725-020897",
    "kind_of_bike": "Damenfahrradrahmen mit Reifen",
    "manufacturer": "unbekannt",
    "model": "Tourenrad",
    "color": "bronzefarben",
    "department": "Direktion 1 Abschnitt 16"
  },
  {
    "url": "https://www.berlin.de/polizei/service/vermissen-sie-ihr-fahrrad/artikel.754097.php",
    "description": "Schwarzer Herrenfahrrad-Rahmen mit Reifen",
    "image": "https://www.berlin.de/polizei/service/vermissen-sie-ihr-fahrrad/fahrradteile/",
    "operation_number": "181001-1143-027370",
    "kind_of_bike": "Herrenfahrrad-Rahmen mit Reifen",
    "manufacturer": "Bike Manufaktur",
    "model": "Magic LX",
    "color": "schwarz",
    "department": "Direktion 3 Abschnitt 32"
  },
  {
    "url": "https://www.berlin.de/polizei/service/vermissen-sie-ihr-fahrrad/artikel.753284.php",
    "description": "Schwarzer Herrenfahrrad-Rahmen mit Reifen",
    "image": "https://www.berlin.de/polizei/service/vermissen-sie-ihr-fahrrad/fahrradteile/",
    "operation_number": "180907-1300-256000",
    "kind_of_bike": "Herrenfahrrad-Rahmen mit Reifen",
    "manufacturer": "Focus",
    "model": "schwarz",
    "color": "Direktion 5 Abschnitt 55"
  },
  {
    "url": "https://www.berlin.de/polizei/service/vermissen-sie-ihr-fahrrad/artikel.753262.php",
    "description": "Schwarzer Herrenfahrrad-Rahmen",
    "image": "https://www.berlin.de/polizei/service/vermissen-sie-ihr-fahrrad/fahrradteile/",
    "operation_number": "180907-1300-256000",
    "kind_of_bike": "Herrenfahrrad-Rahmen",
    "manufacturer": "unbekannt",
    "model": "schwarz",
    "color": "Direktion 5 Abschnitt 55"
  },
  {
    "url": "https://www.berlin.de/polizei/service/vermissen-sie-ihr-fahrrad/artikel.753246.php",
    "description": "Schwarzer Damenfahrrad-Rahmen mit Reifen",
    "image": "https://www.berlin.de/polizei/service/vermissen-sie-ihr-fahrrad/fahrradteile/",
    "operation_number": "180907-1300-256000",
    "kind_of_bike": "Damenfahrrad-Rahmen mit Reifen",
    "manufacturer": "Morrison",
    "model": "T 2.0",
    "color": "schwarz",
    "department": "Direktion 5 Abschnitt 55"
  },
  {
    "url": "https://www.berlin.de/polizei/service/vermissen-sie-ihr-fahrrad/artikel.753230.php",
    "description": "Schwarzer Fahrradrahmen",
    "image": "https://www.berlin.de/polizei/service/vermissen-sie-ihr-fahrrad/fahrradteile/",
    "operation_number": "180907-1300-256000",
    "kind_of_bike": "Fahrradrahmen Damenfahrrad",
    "manufacturer": "Velo Ville",
    "model": "schwarz",
    "color": "Direktion 5 Abschnitt 55"
  },
  {
    "url": "https://www.berlin.de/polizei/service/vermissen-sie-ihr-fahrrad/artikel.753221.php",
    "description": "Schwarzer Herrenfahrrad-Rahmen mit einem Reifen",
    "image": "https://www.berlin.de/polizei/service/vermissen-sie-ihr-fahrrad/fahrradteile/",
    "operation_number": "180907-1300-256000",
    "kind_of_bike": "Herrenfahrrad-Rahmen mit einem Reifen",
    "manufacturer": "Bike Manufaktur",
    "model": "Black Cross",
    "color": "schwarz",
    "department": "Direktion 5 Abschnitt 55"
  },
  {
    "url": "https://www.berlin.de/polizei/service/vermissen-sie-ihr-fahrrad/artikel.753210.php",
    "description": "Grauer Fahrradrahmen mit einem Reifen",
    "image": "https://www.berlin.de/polizei/service/vermissen-sie-ihr-fahrrad/fahrradteile/",
    "operation_number": "180907-1300-256000",
    "kind_of_bike": "Fahrradrahmen mit einem Reifen",
    "manufacturer": "Cannondale",
    "model": "CX Quick",
    "color": "grau",
    "department": "Direktion 5 Abschnitt 55"
  },
  {
    "url": "https://www.berlin.de/polizei/service/vermissen-sie-ihr-fahrrad/artikel.751643.php",
    "description": "Schwarz-wei\u00dfer Fahrradrahmen mit Reifen",
    "image": "https://www.berlin.de/polizei/service/vermissen-sie-ihr-fahrrad/fahrradteile/",
    "operation_number": "180509-1529-231120",
    "manufacturer": "Bulls",
    "model": "Styx",
    "color": "schwarz mit wei\u00dfer und gr\u00fcner Schrift",
    "department": "Direktion 3 Abschnitt 36"
  },
  {
    "url": "https://www.berlin.de/polizei/service/vermissen-sie-ihr-fahrrad/artikel.751628.php",
    "description": "Schwarzer Fahrradrahmen mit Reifen",
    "image": "https://www.berlin.de/polizei/service/vermissen-sie-ihr-fahrrad/fahrradteile/",
    "operation_number": "180509-1529-231120",
    "kind_of_bike": "Fahrradrahmen",
    "manufacturer": "Kettler",
    "model": "Modena Sport",
    "color": "schwarz",
    "department": "Direktion 3 Abschnitt 36"
  },
  {
    "url": "https://www.berlin.de/polizei/service/vermissen-sie-ihr-fahrrad/artikel.745071.php",
    "description": "Schwarzer Fahrradrahmen",
    "image": "https://www.berlin.de/polizei/service/vermissen-sie-ihr-fahrrad/fahrradteile/",
    "operation_number": "180914-0434-030329",
    "kind_of_bike": "unbekannt",
    "manufacturer": "Direktion 1 Abschnitt 12"
  },
  {
    "url": "https://www.berlin.de/polizei/service/vermissen-sie-ihr-fahrrad/artikel.744967.php",
    "description": "Wei\u00dfer Rahmen mit Reifen",
    "image": "https://www.berlin.de/polizei/service/vermissen-sie-ihr-fahrrad/fahrradteile/",
    "operation_number": "180914-0434-030329",
    "kind_of_bike": "Steppenwolf",
    "manufacturer": "Direktion 1 Abschnitt 12"
  },
  {
    "url": "https://www.berlin.de/polizei/service/vermissen-sie-ihr-fahrrad/artikel.705151.php",
    "description": "Vorderrad Damenfahrrad",
    "image": "https://www.berlin.de/polizei/service/vermissen-sie-ihr-fahrrad/fahrradteile/",
    "operation_number": "180510-0300-025106",
    "kind_of_bike": "Fahrradteile/ Vorderrad Damenfahrrad",
    "manufacturer": "Freedom",
    "model": "Direktion 2 Abschnitt 21"
  },
  {
    "url": "https://www.berlin.de/polizei/service/vermissen-sie-ihr-fahrrad/artikel.693960.php",
    "description": "Blauer Rahmen",
    "image": "https://www.berlin.de/polizei/service/vermissen-sie-ihr-fahrrad/fahrradteile/",
    "operation_number": "180316-0030-285865",
    "kind_of_bike": "Funk",
    "manufacturer": "Direktion 2 Abschnitt 21"
  },
  {
    "url": "https://www.berlin.de/polizei/service/vermissen-sie-ihr-fahrrad/artikel.693955.php",
    "description": "Roter Fahrradrahmen",
    "image": "https://www.berlin.de/polizei/service/vermissen-sie-ihr-fahrrad/fahrradteile/",
    "operation_number": "180316-0030-285865",
    "kind_of_bike": "Cannondale",
    "manufacturer": "Direktion 2 Abschnitt 21"
  },
  {
    "url": "https://www.berlin.de/polizei/service/vermissen-sie-ihr-fahrrad/artikel.693952.php",
    "description": "Schwarz-goldener Rahmen",
    "image": "https://www.berlin.de/polizei/service/vermissen-sie-ihr-fahrrad/fahrradteile/",
    "operation_number": "180316-0030-285865",
    "kind_of_bike": "Scott",
    "manufacturer": "Direktion 2 Abschnitt 21"
  },
  {
    "url": "https://www.berlin.de/polizei/service/vermissen-sie-ihr-fahrrad/artikel.693948.php",
    "description": "Schwarzer Fahrradrahmen",
    "image": "https://www.berlin.de/polizei/service/vermissen-sie-ihr-fahrrad/fahrradteile/",
    "operation_number": "180316-0030-285865",
    "kind_of_bike": "Bulls",
    "manufacturer": "Direktion 2 Abschnitt 21"
  },
  {
    "url": "https://www.berlin.de/polizei/service/vermissen-sie-ihr-fahrrad/artikel.693946.php",
    "description": "Schwarzer Mountainbike-Rahmen",
    "image": "https://www.berlin.de/polizei/service/vermissen-sie-ihr-fahrrad/fahrradteile/",
    "operation_number": "180316-0030-285865",
    "kind_of_bike": "Mountainbike-Rahmen",
    "model": "schwarz",
    "color": "Direktion 2 Abschnitt 21"
  },
  {
    "url": "https://www.berlin.de/polizei/service/vermissen-sie-ihr-fahrrad/artikel.693943.php",
    "description": "Schwarzer E-Bike Rahmen",
    "image": "https://www.berlin.de/polizei/service/vermissen-sie-ihr-fahrrad/fahrradteile/",
    "operation_number": "180316-0030-285865",
    "kind_of_bike": "E-Bike Rahmen",
    "manufacturer": "Bulls",
    "model": "schwarz",
    "color": "Direktion 2 Abschnitt 21"
  },
  {
    "url": "https://www.berlin.de/polizei/service/vermissen-sie-ihr-fahrrad/artikel.693941.php",
    "description": "Schwarz-wei\u00dfer Rahmen (Kinderfahrrad)",
    "image": "https://www.berlin.de/polizei/service/vermissen-sie-ihr-fahrrad/fahrradteile/",
    "operation_number": "180316-0030-285865",
    "kind_of_bike": "Focus",
    "manufacturer": "Direktion 2 Abschnitt 21"
  },
  {
    "url": "https://www.berlin.de/polizei/service/vermissen-sie-ihr-fahrrad/artikel.693935.php",
    "description": "Hellgrauer Rahmen",
    "image": "https://www.berlin.de/polizei/service/vermissen-sie-ihr-fahrrad/fahrradteile/",
    "operation_number": "180316-0030-285865",
    "kind_of_bike": "Cannondale",
    "manufacturer": "silkcity",
    "model": "Direktion 2 Abschnitt 21"
  },
  {
    "url": "https://www.berlin.de/polizei/service/vermissen-sie-ihr-fahrrad/artikel.693932.php",
    "description": "Hellblauer Rahmen",
    "image": "https://www.berlin.de/polizei/service/vermissen-sie-ihr-fahrrad/fahrradteile/",
    "operation_number": "180316-0030-285865",
    "kind_of_bike": "unbekannt",
    "manufacturer": "Direktion 2 Abschnitt 21"
  },
  {
    "url": "https://www.berlin.de/polizei/service/vermissen-sie-ihr-fahrrad/artikel.688565.php",
    "description": "Roter Mountainbike Fahrradrahmen",
    "image": "https://www.berlin.de/polizei/service/vermissen-sie-ihr-fahrrad/fahrradteile/",
    "operation_number": "180320-0801-027768",
    "kind_of_bike": "Mountainbike Fahrradrahmen",
    "manufacturer": "Mc Kenzie",
    "model": "rot",
    "color": "Direktion 2 Abschnitt 21"
  }
]